wallstreet/__init__.py
wallstreet/blackandscholes.py
wallstreet/constants.py
wallstreet/wallstreet.py
wallstreet-0.4.0.dist-info/LICENSE
wallstreet-0.4.0.dist-info/METADATA
wallstreet-0.4.0.dist-info/WHEEL
wallstreet-0.4.0.dist-info/RECORD
